MANIFEST.in
README.md
setup.py
social_services/__init__.py
social_services/app_registry.py
social_services/forms.py
social_services/models.py
social_services/urlhelper.py
social_services/urls.py
social_services/utils.py
social_services/views.py
social_services/migrations/0001_initial.py
social_services/migrations/__init__.py
social_services/static/css/jquery.jqplot.min.css
social_services/static/css/social_services.css
social_services/static/js/jqplot.pieRenderer.min.js
social_services/static/js/jquery.jqplot.min.js
social_services/static/js/social_service_map.js
social_services/static/js/social_service_map.js.orig
social_services/static/js/social_service_responder_charts.js
social_services/templates/social_services/base-wide.html
social_services/templates/social_services/base.html
social_services/templates/social_services/map.html
social_services/templates/social_services/nav.html
social_services/templates/social_services/profile.html
social_services/templates/social_services/relief-area-detail.html
social_services/templates/social_services/relief-areas.html
social_services/templates/social_services/relief_form.html
social_services/templates/social_services/responders.html
social_services/templates/social_services/skills.html
social_services/templatetags/__init__.py
social_services/templatetags/social_services_tags.py
tendenci_social_services.egg-info/PKG-INFO
tendenci_social_services.egg-info/SOURCES.txt
tendenci_social_services.egg-info/dependency_links.txt
tendenci_social_services.egg-info/requires.txt
tendenci_social_services.egg-info/top_level.txt