Metadata-Version: 1.0
Name: tendenci-social-services
Version: 1.0.0
Summary: Social Services addon for Tendenci
Home-page: https://github.com/tendenci/tendenci-social-services
Author: Schipul
Author-email: programmers@schipul.com
License: GPL3
Platform: UNKNOWN
Classifier: Development Status :: 5 - Production/Stable
Classifier: Environment :: Web Environment
Classifier: Framework :: Django
Classifier: Intended Audience :: Developers
Classifier: License :: OSI Approved :: GNU General Public License v3 (GPLv3)
Classifier: Operating System :: OS Independent
Classifier: Programming Language :: Python
Classifier: Topic :: Internet :: WWW/HTTP
Classifier: Topic :: Internet :: WWW/HTTP :: Dynamic Content
